{
  "default": "2b449a5d-244e-4a0c-bd82-562ad5340db1",
  "presets": [
    {
      "id": "661a7325-e301-4c5e-8baa-ec37c17441df",
      "name": "Amherst",
      "configuration": {
        "start": "2018-12-30",
        "reset": "SUNDAY",
        "items": [
          {
            "item": "GARBAGE",
            "enabled": true
          },
          {
            "item": "RECYCLING",
            "enabled": true
          }
        ],
        "leapDays": [
          "2019-01-01",
          "2019-05-27",
          "2019-07-04",
          "2019-09-02",
          "2019-11-28",
          "2019-12-25",
          "2020-01-01"
        ]
      }
    },
    {
      "id": "2b449a5d-244e-4a0c-bd82-562ad5340db1",
      "name": "Buffalo",
      "configuration": {
        "start": "2018-12-30",
        "reset": "SUNDAY",
        "items": [
          {
            "item": "GARBAGE",
            "enabled": true
          },
          {
            "item": "RECYCLING",
            "enabled": true
          }
        ],
        "holidays": [
          "2019-12-25",
          "2020-01-01"
        ]
      }
    },
    {
      "id": "018fff06-5181-4421-802d-c0063f16e799",
      "name": "Cheektowaga",
      "configuration": {
        "start": "2018-04-08",
        "reset": "SUNDAY",
        "items": [
          {
            "item": "GARBAGE",
            "enabled": true
          },
          {
            "item": "RECYCLING",
            "enabled": true,
            "weeks": [
              "A",
              "B"
            ]
          }
        ],
        "leapDays": [
          "2019-12-25",
          "2020-01-01"
        ]
      }
    },
    {
      "id": "fcf318fa-e0bd-422f-9d1e-6e346ac339f0",
      "name": "Lackawanna",
      "configuration": {
        "start": "2018-12-30",
        "reset": "SUNDAY",
        "items": [
          {
            "item": "GARBAGE",
            "enabled": true
          },
          {
            "item": "RECYCLING",
            "enabled": true
          }
        ],
        "bulkDays": [
          "2019-04-08",
          "2020-09-16"
        ],
        "leapDays": [
          "2019-12-25",
          "2020-01-01"
        ]
      }
    },
    {
      "id": "1fe69b89-3523-4ab5-9ab5-5447e8566dfe",
      "name": "Orchard Park",
      "configuration": {
        "start": "2018-12-30",
        "reset": "SUNDAY",
        "items": [
          {
            "item": "GARBAGE",
            "enabled": true
          },
          {
            "item": "RECYCLING",
            "enabled": true,
            "weeks": [
              "White",
              "Shaded"
            ]
          }
        ],
        "leapDays": [
          "2019-01-01",
          "2019-05-27",
          "2019-07-04",
          "2019-09-02",
          "2019-11-28",
          "2019-12-25",
          "2020-01-01"
        ]
      }
    },
    {
      "id": "1eea6061-63f4-462b-bf97-70e84141f405",
      "name": "West Seneca",
      "configuration": {
        "start": "2019-05-01",
        "reset": "SUNDAY",
        "items": [
          {
            "item": "GARBAGE",
            "enabled": true
          },
          {
            "item": "RECYCLING",
            "enabled": true,
            "weeks": [
              "A",
              "B"
            ]
          }
        ],
        "leapDays": [
          "2019-05-27",
          "2019-07-04",
          "2019-09-02",
          "2019-11-28",
          "2019-12-25",
          "2020-01-01"
        ]
      }
    },
    {
      "id": "80a82401-bcef-44f6-937a-899969f3e610",
      "name": "Lancaster",
      "configuration": {
        "start": "2019-02-04",
        "reset": "SUNDAY",
        "items": [
          {
            "item": "GARBAGE",
            "enabled": true
          },
          {
            "item": "RECYCLING",
            "enabled": true,
            "weeks": [
              "Gold",
              "Green"
            ]
          }
        ],
        "leapDays": [
          "2019-05-27",
          "2019-07-04",
          "2019-09-02",
          "2019-11-28",
          "2019-12-25",
          "2020-01-01"
        ]
      }
    },
    {
      "id": "08ff1376-d840-4e28-b1ab-51024500c07a",
      "name": "Lockport",
      "configuration": {
        "start": "2019-01-06",
        "reset": "SUNDAY",
        "items": [
          {
            "item": "GARBAGE",
            "enabled": true
          },
          {
            "item": "RECYCLING",
            "enabled": true,
            "weeks": [
              "A",
              "B"
            ]
          }
        ],
        "leapDays": [
          "2019-01-01",
          "2019-05-27",
          "2019-07-04",
          "2019-09-02",
          "2019-11-28",
          "2019-12-25",
          "2020-01-01"
        ]
      }
    },
    {
      "id": "80120493-76ac-4c13-ab31-beccae633bf8",
      "name": "Akron",
      "configuration": {
        "start": "2019-01-06",
        "reset": "SUNDAY",
        "items": [
          {
            "item": "GARBAGE",
            "enabled": true
          },
          {
            "item": "RECYCLING",
            "enabled": true,
            "weeks": [
              "A",
              "B"
            ]
          }
        ],
        "leapDays": [
          "2019-01-01",
          "2019-05-27",
          "2019-07-04",
          "2019-09-02",
          "2019-11-28",
          "2019-12-25",
          "2020-01-01"
        ]
      }
    },
    {
      "id": "cac4b43c-abd9-48fc-a4ad-ae44632f85ff",
      "name": "Evans",
      "configuration": {
        "start": "2019-01-13",
        "reset": "SUNDAY",
        "items": [
          {
            "item": "GARBAGE",
            "enabled": true
          },
          {
            "item": "RECYCLING",
            "enabled": true,
            "weeks": [
              "A",
              "B"
            ]
          }
        ],
        "leapDays": [
          "2019-01-01",
          "2019-05-27",
          "2019-07-04",
          "2019-09-02",
          "2019-11-28",
          "2019-12-25",
          "2020-01-01"
        ]
      }
    },
    {
      "id": "239c1383-9978-402a-8938-2f5221f7cc9a",
      "name": "Angola",
      "configuration": {
        "start": "2019-01-06",
        "reset": "SUNDAY",
        "items": [
          {
            "item": "GARBAGE",
            "enabled": true
          },
          {
            "item": "RECYCLING",
            "enabled": true
          }
        ],
        "leapDays": [
          "2019-01-01",
          "2019-05-27",
          "2019-07-04",
          "2019-09-02",
          "2019-12-25",
          "2020-01-01"
        ]
      }
    }
  ]
}
